py_extrema/__init__.py
py_extrema/extrema.py
py_extrema/slopping_saddle.py
py_extrema/utils.py
py_extrema-0.0.3.dist-info/LICENSE.txt
py_extrema-0.0.3.dist-info/METADATA
py_extrema-0.0.3.dist-info/WHEEL
py_extrema-0.0.3.dist-info/top_level.txt
py_extrema-0.0.3.dist-info/RECORD
