Metadata-Version: 2.1
Name: py-extrema
Version: 0.0.3
Summary: Find extrema and their mergers in N dimensional fields.
Home-page: https://github.com/cphyc/py_extrema
Author: Corentin Cadiou
Author-email: contact@cphyc.me
License: UNKNOWN
Platform: UNKNOWN
Classifier: Development Status :: 4 - Beta
Classifier: License :: OSI Approved :: CEA CNRS Inria Logiciel Libre License, version 2.1 (CeCILL-2.1)
Classifier: Programming Language :: Python
Classifier: Programming Language :: Python :: 3
Classifier: Programming Language :: Python :: 3.6
Classifier: Programming Language :: Python :: Implementation :: CPython
Classifier: Programming Language :: Python
Classifier: Topic :: Scientific/Engineering :: Astronomy
Classifier: Topic :: Scientific/Engineering :: Physics
Classifier: Topic :: Scientific/Engineering :: Information Analysis
Requires-Python: >=3.6.0
Requires-Dist: numpy
Requires-Dist: numba
Requires-Dist: unyt
Requires-Dist: scipy
Requires-Dist: pandas
Requires-Dist: pyfftw
Requires-Dist: tqdm
Requires-Dist: numexpr
